hello.py
nickspophello-0.0.3.dist-info/DESCRIPTION.rst
nickspophello-0.0.3.dist-info/METADATA
nickspophello-0.0.3.dist-info/RECORD
nickspophello-0.0.3.dist-info/WHEEL
nickspophello-0.0.3.dist-info/entry_points.txt
nickspophello-0.0.3.dist-info/metadata.json
nickspophello-0.0.3.dist-info/top_level.txt
