Metadata-Version: 2.0
Name: nickspophello
Version: 0.0.3
Summary: a module / utility to print Hello World.
Home-page: https://github.com/nickcresner/helloWorld.py.git
Author: Nick Cresner
Author-email: nickcresner@gmail.com
License: MIT
Platform: UNKNOWN
